scrat/__init__.py
scrat/cli/__init__.py
scrat/cli/setup.py
scrat/cli/stash.py
scrat/config.py
scrat/db/__init__.py
scrat/db/connector.py
scrat/db/models.py
scrat/decorator.py
scrat/hasher/__init__.py
scrat/hasher/base.py
scrat/hasher/iterable.py
scrat/hasher/manager.py
scrat/hasher/numpy.py
scrat/hasher/pandas.py
scrat/hasher/to_string.py
scrat/serializer/__init__.py
scrat/serializer/base.py
scrat/serializer/dill.py
scrat/serializer/json.py
scrat/serializer/numpy.py
scrat/serializer/pandas.py
scrat/serializer/pickle.py
scrat/squirrel.py
scrat/utils/__init__.py
scrat/utils/timer.py
scrat-0.3.0.dist-info/LICENSE
scrat-0.3.0.dist-info/METADATA
scrat-0.3.0.dist-info/WHEEL
scrat-0.3.0.dist-info/entry_points.txt
scrat-0.3.0.dist-info/RECORD
